prodcon/__init__.py
prodcon/prodcon.py
prodcon-0.2.0.dist-info/LICENSE
prodcon-0.2.0.dist-info/METADATA
prodcon-0.2.0.dist-info/WHEEL
prodcon-0.2.0.dist-info/top_level.txt
prodcon-0.2.0.dist-info/RECORD
