Metadata-Version: 2.1
Name: prodcon
Version: 0.2.0
Summary: An easy to use implementation of the producer consumer pattern
Home-page: https://github.com/JohannesPertl/prodcon
Author: Johannes Pertl
Author-email: johannes.pertl@edu.fh-joanneum.at
License: UNKNOWN
Platform: UNKNOWN
Classifier: Programming Language :: Python :: 3
Classifier: License :: OSI Approved :: GNU General Public License v3 (GPLv3)
Classifier: Operating System :: OS Independent
Requires-Python: >=3.6
